statistics_distributions/Binomialdistribution.py
statistics_distributions/Gaussiandistribution.py
statistics_distributions/Generaldistribution.py
statistics_distributions/__init__.py
statistics_distributions-0.1.dist-info/DESCRIPTION.rst
statistics_distributions-0.1.dist-info/METADATA
statistics_distributions-0.1.dist-info/RECORD
statistics_distributions-0.1.dist-info/WHEEL
statistics_distributions-0.1.dist-info/metadata.json
statistics_distributions-0.1.dist-info/top_level.txt
