Metadata-Version: 2.0
Name: statistics-distributions
Version: 0.1
Summary: Gaussian Distribution and Binomial Distribution
Home-page: UNKNOWN
Author: UNKNOWN
Author-email: UNKNOWN
License: UNKNOWN
Platform: UNKNOWN
